{
  "items" : {
    "-KAvQZkv78nZ25G7zyH0" : {
      "country" : "Spain",
      "distance" : "500",
      "name" : "Andreas",
      "postalCode" : "28004"
    },
    "-KAwXjLQLIx5asez-Usa" : {
      "country" : "canada",
      "distance" : "100",
      "name" : "marko",
      "postalCode" : "m5v3g8"
    },
    "-KAwXv_d4CXHQrz7xS_0" : {
      "country" : "USA",
      "distance" : "100",
      "name" : "Eduardo Gonzalez",
      "postalCode" : "94596"
    },
    "-KAwY2fSKwLmaQB0Dgoq" : {
      "country" : "USA",
      "distance" : "50",
      "name" : "Jon",
      "postalCode" : "92657"
    },
    "-KAwZGjhRo_ywWu9mKZs" : {
      "country" : "United States",
      "distance" : "40",
      "name" : "Martin Wilter",
      "postalCode" : "98012"
    },
    "-KAwe4Jaqxai3h_b4Hzw" : {
      "country" : "US",
      "distance" : "50",
      "name" : "Corey",
      "postalCode" : "45430"
    },
    "-KAwfmcXsmA6ToloitAj" : {
      "country" : "USA",
      "distance" : "50",
      "name" : "Dallas",
      "postalCode" : "73013"
    },
    "-KAwiPYMxaW7eAQEIIdC" : {
      "country" : "usa",
      "distance" : "50",
      "name" : "uv",
      "postalCode" : "94555"
    },
    "-KAwkC6Hpic1eyTg28T3" : {
      "country" : "USA",
      "distance" : "25",
      "name" : "Andy",
      "postalCode" : "98177"
    },
    "-KAwkrFHK4PzJl7XZzpT" : {
      "country" : "USA",
      "distance" : "100",
      "name" : "Ravi",
      "postalCode" : "70820"
    },
    "-KAwlT0dmVdGt2GodRRJ" : {
      "country" : "United States",
      "distance" : "40",
      "name" : "Eric Martz",
      "postalCode" : "30214"
    },
    "-KAwp03FcRPuApQsR9_O" : {
      "country" : "Austria",
      "distance" : "20040",
      "name" : "martin-martin",
      "postalCode" : "8480"
    },
    "-KAwpDw4c_VU2Np86Btb" : {
      "country" : "USA",
      "distance" : "30",
      "name" : "Kyle",
      "postalCode" : "30316"
    },
    "-KAwrU-EHaU8CzVp1Z2H" : {
      "country" : "USA",
      "distance" : "40",
      "name" : "Jim",
      "postalCode" : "55311"
    },
    "-KAwto2cFhPHJWcZKbSY" : {
      "country" : "US",
      "distance" : "40",
      "name" : "Kacyn",
      "postalCode" : "95014"
    },
    "-KAwww6OFXAYSS2SXIHg" : {
      "country" : "India",
      "distance" : "10",
      "name" : "Shouvik",
      "postalCode" : "122001"
    },
    "-KAwyosV7zVEtPZ6dOQ_" : {
      "country" : "Australia",
      "distance" : "500",
      "name" : "Mat",
      "postalCode" : "2870"
    },
    "-KAwz1mEfyrHGRFSSKKq" : {
      "country" : "USA",
      "distance" : "30",
      "name" : "Randeep",
      "postalCode" : "94085"
    },
    "-KAx3Ps87BYocmO3juKB" : {
      "country" : "USA",
      "distance" : "30",
      "name" : "Natasha Japp",
      "postalCode" : "80033"
    },
    "-KAx9wu5pBYlsqMSAUC_" : {
      "country" : "United States",
      "distance" : "20",
      "name" : "Mark",
      "postalCode" : "19145"
    },
    "-KAxFliLkVFZJ6aKyDoB" : {
      "country" : "USA",
      "distance" : "10",
      "name" : "MsLaura",
      "postalCode" : "95070"
    },
    "-KAxQbSC_1-HB-8eBbxM" : {
      "country" : "India",
      "distance" : "20",
      "name" : "Harshit",
      "postalCode" : "110091"
    },
    "-KAxW4I369uV5BNEYutz" : {
      "country" : "South Korea",
      "distance" : "20000",
      "name" : "Yoongu Hwang",
      "postalCode" : "14306"
    },
    "-KAxi1FmdkAAdWYUl-cq" : {
      "country" : "Russia",
      "distance" : "50",
      "name" : "A",
      "postalCode" : "142190"
    }
  }
}
